odoo/addons/project_role/README.rst
odoo/addons/project_role/__init__.py
odoo/addons/project_role/__manifest__.py
odoo/addons/project_role/i18n/de.po
odoo/addons/project_role/i18n/es_AR.po
odoo/addons/project_role/i18n/es_PA.po
odoo/addons/project_role/i18n/fr.po
odoo/addons/project_role/i18n/it.po
odoo/addons/project_role/i18n/project_role.pot
odoo/addons/project_role/i18n/sl.po
odoo/addons/project_role/models/__init__.py
odoo/addons/project_role/models/project_assignment.py
odoo/addons/project_role/models/project_project.py
odoo/addons/project_role/models/project_role.py
odoo/addons/project_role/models/res_company.py
odoo/addons/project_role/models/res_config_settings.py
odoo/addons/project_role/readme/CONFIGURE.rst
odoo/addons/project_role/readme/CONTRIBUTORS.rst
odoo/addons/project_role/readme/DESCRIPTION.rst
odoo/addons/project_role/security/ir.model.access.csv
odoo/addons/project_role/security/project_role.xml
odoo/addons/project_role/static/description/icon.png
odoo/addons/project_role/static/description/index.html
odoo/addons/project_role/tests/__init__.py
odoo/addons/project_role/tests/test_project_role.py
odoo/addons/project_role/views/project_assignment.xml
odoo/addons/project_role/views/project_project.xml
odoo/addons/project_role/views/project_role.xml
odoo/addons/project_role/views/res_config_settings.xml
odoo14_addon_project_role-14.0.1.0.1.dist-info/METADATA
odoo14_addon_project_role-14.0.1.0.1.dist-info/WHEEL
odoo14_addon_project_role-14.0.1.0.1.dist-info/top_level.txt
odoo14_addon_project_role-14.0.1.0.1.dist-info/RECORD
